[
  {
    "Line": "102",
    "V": 18.7725
  },
  {
    "Line": "103",
    "V": 21.6662
  },
  {
    "Line": "104",
    "V": 23.429
  },
  {
    "Line": "105",
    "V": 22.018
  },
  {
    "Line": "107",
    "V": 21.0453
  },
  {
    "Line": "108",
    "V": 22.8654
  },
  {
    "Line": "109",
    "V": 26.8716
  },
  {
    "Line": "110",
    "V": 22.6976
  },
  {
    "Line": "111",
    "V": 27.5742
  },
  {
    "Line": "112",
    "V": 24.1785
  },
  {
    "Line": "114",
    "V": 27.8079
  },
  {
    "Line": "115",
    "V": 26.7518
  },
  {
    "Line": "116",
    "V": 72.2084
  },
  {
    "Line": "117",
    "V": 20.7915
  },
  {
    "Line": "118",
    "V": 24.4119
  },
  {
    "Line": "119",
    "V": 24.201
  },
  {
    "Line": "120",
    "V": 21.5161
  },
  {
    "Line": "121",
    "V": 24.9124
  },
  {
    "Line": "122",
    "V": 22.1518
  },
  {
    "Line": "124",
    "V": 20.2876
  },
  {
    "Line": "125",
    "V": 31.7353
  },
  {
    "Line": "126",
    "V": 25.7496
  },
  {
    "Line": "127",
    "V": 21.7224
  },
  {
    "Line": "128",
    "V": 29.8785
  },
  {
    "Line": "129",
    "V": 20.8412
  },
  {
    "Line": "131",
    "V": 23.2506
  },
  {
    "Line": "132",
    "V": 26.7696
  },
  {
    "Line": "133",
    "V": 26.9839
  },
  {
    "Line": "134",
    "V": 30.7302
  },
  {
    "Line": "136",
    "V": 20.4268
  },
  {
    "Line": "138",
    "V": 21.8831
  },
  {
    "Line": "139",
    "V": 29.4234
  },
  {
    "Line": "140",
    "V": 25.3014
  },
  {
    "Line": "141",
    "V": 21.3599
  },
  {
    "Line": "143",
    "V": 24.158
  },
  {
    "Line": "145",
    "V": 22.457
  },
  {
    "Line": "146",
    "V": 26.0401
  },
  {
    "Line": "147",
    "V": 23.9079
  },
  {
    "Line": "148",
    "V": 23.5185
  },
  {
    "Line": "149",
    "V": 21.7576
  },
  {
    "Line": "151",
    "V": 23.8277
  },
  {
    "Line": "152",
    "V": 26.7395
  },
  {
    "Line": "153",
    "V": 32.2968
  },
  {
    "Line": "154",
    "V": 42.3814
  },
  {
    "Line": "155",
    "V": 21.849
  },
  {
    "Line": "156",
    "V": 22.9213
  },
  {
    "Line": "157",
    "V": 20.5449
  },
  {
    "Line": "158",
    "V": 20.6625
  },
  {
    "Line": "159",
    "V": 20.1546
  },
  {
    "Line": "160",
    "V": 22.9847
  },
  {
    "Line": "161",
    "V": 78.3628
  },
  {
    "Line": "162",
    "V": 25.5315
  },
  {
    "Line": "163",
    "V": 26.1889
  },
  {
    "Line": "164",
    "V": 63.0162
  },
  {
    "Line": "165",
    "V": 20.7638
  },
  {
    "Line": "166",
    "V": 25.208
  },
  {
    "Line": "167",
    "V": 44.3149
  },
  {
    "Line": "168",
    "V": 23.1833
  },
  {
    "Line": "169",
    "V": 18.6344
  },
  {
    "Line": "170",
    "V": 17.7751
  },
  {
    "Line": "171",
    "V": 24.9033
  },
  {
    "Line": "172",
    "V": 19.4427
  },
  {
    "Line": "173",
    "V": 25.2775
  },
  {
    "Line": "174",
    "V": 18.6343
  },
  {
    "Line": "175",
    "V": 21.4962
  },
  {
    "Line": "176",
    "V": 26.4704
  },
  {
    "Line": "177",
    "V": 21.0534
  },
  {
    "Line": "178",
    "V": 19.4135
  },
  {
    "Line": "179",
    "V": 22.392
  },
  {
    "Line": "180",
    "V": 22.4092
  },
  {
    "Line": "182",
    "V": 26.0776
  },
  {
    "Line": "183",
    "V": 23.978
  },
  {
    "Line": "184",
    "V": 23.4929
  },
  {
    "Line": "185",
    "V": 30.9376
  },
  {
    "Line": "186",
    "V": 51.2689
  },
  {
    "Line": "187",
    "V": 22.869
  },
  {
    "Line": "188",
    "V": 23.9415
  },
  {
    "Line": "189",
    "V": 24.3447
  },
  {
    "Line": "190",
    "V": 22.9252
  },
  {
    "Line": "191",
    "V": 22.5061
  },
  {
    "Line": "192",
    "V": 22.7852
  },
  {
    "Line": "193",
    "V": 23.1343
  },
  {
    "Line": "194",
    "V": 24.1462
  },
  {
    "Line": "195",
    "V": 22.2187
  },
  {
    "Line": "196",
    "V": 24.5486
  },
  {
    "Line": "197",
    "V": 23.1286
  },
  {
    "Line": "198",
    "V": 27.1226
  },
  {
    "Line": "199",
    "V": 22.5409
  },
  {
    "Line": "201",
    "V": 26.376
  },
  {
    "Line": "202",
    "V": 20.8027
  },
  {
    "Line": "203",
    "V": 20.5751
  },
  {
    "Line": "204",
    "V": 21.9823
  },
  {
    "Line": "205",
    "V": 20.2398
  },
  {
    "Line": "206",
    "V": 19.3494
  },
  {
    "Line": "207",
    "V": 22.5963
  },
  {
    "Line": "208",
    "V": 18.2994
  },
  {
    "Line": "209",
    "V": 21.6321
  },
  {
    "Line": "211",
    "V": 25.5065
  },
  {
    "Line": "212",
    "V": 18.9496
  },
  {
    "Line": "213",
    "V": 27.9928
  },
  {
    "Line": "214",
    "V": 26.1209
  },
  {
    "Line": "217",
    "V": 20.8749
  },
  {
    "Line": "218",
    "V": 16.9287
  },
  {
    "Line": "219",
    "V": 29.0874
  },
  {
    "Line": "221",
    "V": 18.7052
  },
  {
    "Line": "222",
    "V": 19.7135
  },
  {
    "Line": "225",
    "V": 21.5331
  },
  {
    "Line": "227",
    "V": 19.1346
  },
  {
    "Line": "240",
    "V": 23.4255
  },
  {
    "Line": "245",
    "V": 21.4211
  },
  {
    "Line": "256",
    "V": 20.7034
  },
  {
    "Line": "303",
    "V": 24.0681
  },
  {
    "Line": "304",
    "V": 26.1721
  },
  {
    "Line": "305",
    "V": 78.9624
  },
  {
    "Line": "306",
    "V": 24.0665
  },
  {
    "Line": "311",
    "V": 20.4069
  },
  {
    "Line": "317",
    "V": 23.9273
  },
  {
    "Line": "320",
    "V": 24.4766
  },
  {
    "Line": "323",
    "V": 20.5953
  },
  {
    "Line": "326",
    "V": 31.4935
  },
  {
    "Line": "331",
    "V": 22.604
  },
  {
    "Line": "332",
    "V": 24.8474
  },
  {
    "Line": "334",
    "V": 28.6797
  },
  {
    "Line": "338",
    "V": 20.2976
  },
  {
    "Line": "340",
    "V": 21.8754
  },
  {
    "Line": "345",
    "V": 20.4244
  },
  {
    "Line": "365",
    "V": 16.4261
  },
  {
    "Line": "397",
    "V": 21.865
  },
  {
    "Line": "401",
    "V": 23.4078
  },
  {
    "Line": "402",
    "V": 25.3376
  },
  {
    "Line": "411",
    "V": 28.5217
  },
  {
    "Line": "412",
    "V": 23.0104
  },
  {
    "Line": "414",
    "V": 25.3568
  },
  {
    "Line": "500",
    "V": 21.3778
  },
  {
    "Line": "501",
    "V": 20.0399
  },
  {
    "Line": "502",
    "V": 29.498
  },
  {
    "Line": "503",
    "V": 24.567
  },
  {
    "Line": "504",
    "V": 21.9384
  },
  {
    "Line": "507",
    "V": 24.8978
  },
  {
    "Line": "509",
    "V": 24.5961
  },
  {
    "Line": "511",
    "V": 31.1117
  },
  {
    "Line": "512",
    "V": 22.7709
  },
  {
    "Line": "514",
    "V": 27.0489
  },
  {
    "Line": "516",
    "V": 25.8199
  },
  {
    "Line": "517",
    "V": 19.5488
  },
  {
    "Line": "518",
    "V": 27.1121
  },
  {
    "Line": "519",
    "V": 22.6692
  },
  {
    "Line": "520",
    "V": 23.947
  },
  {
    "Line": "521",
    "V": 26.8493
  },
  {
    "Line": "522",
    "V": 21.8466
  },
  {
    "Line": "523",
    "V": 25.017
  },
  {
    "Line": "525",
    "V": 24.9101
  },
  {
    "Line": "527",
    "V": 24.622
  },
  {
    "Line": "700",
    "V": 25.7395
  },
  {
    "Line": "702",
    "V": 26.8366
  },
  {
    "Line": "703",
    "V": 34.3759
  },
  {
    "Line": "704",
    "V": 26.4282
  },
  {
    "Line": "705",
    "V": 35.3848
  },
  {
    "Line": "706",
    "V": 27.2159
  },
  {
    "Line": "708",
    "V": 22.4521
  },
  {
    "Line": "709",
    "V": 24.9822
  },
  {
    "Line": "710",
    "V": 26.3263
  },
  {
    "Line": "711",
    "V": 32.2025
  },
  {
    "Line": "713",
    "V": 25.5806
  },
  {
    "Line": "715",
    "V": 27.6592
  },
  {
    "Line": "716",
    "V": 22.2981
  },
  {
    "Line": "719",
    "V": 24.5539
  },
  {
    "Line": "720",
    "V": 33.1234
  },
  {
    "Line": "721",
    "V": 35.566
  },
  {
    "Line": "722",
    "V": 27.7044
  },
  {
    "Line": "723",
    "V": 29.1273
  },
  {
    "Line": "727",
    "V": 24.1217
  },
  {
    "Line": "728",
    "V": 27.8217
  },
  {
    "Line": "730",
    "V": 32.9128
  },
  {
    "Line": "731",
    "V": 27.2448
  },
  {
    "Line": "733",
    "V": 41.191
  },
  {
    "Line": "734",
    "V": 34.4866
  },
  {
    "Line": "736",
    "V": 30.5914
  },
  {
    "Line": "737",
    "V": 26.5537
  },
  {
    "Line": "738",
    "V": 26.8453
  },
  {
    "Line": "739",
    "V": 24.7649
  },
  {
    "Line": "741",
    "V": 29.3184
  },
  {
    "Line": "742",
    "V": 27.7492
  },
  {
    "Line": "900",
    "V": 15.926
  },
  {
    "Line": "E-1",
    "V": 86.4809
  },
  {
    "Line": "E-2",
    "V": 22.8102
  },
  {
    "Line": "E-7",
    "V": 26.8277
  },
  {
    "Line": "E-9",
    "V": 30.3258
  },
  {
    "Line": "L-2",
    "V": 17.0986
  },
  {
    "Line": "L-4",
    "V": 24.2351
  },
  {
    "Line": "L-5",
    "V": 20.0194
  },
  {
    "Line": "L-6",
    "V": 32.4714
  },
  {
    "Line": "L-7",
    "V": 28.0693
  },
  {
    "Line": "L-8",
    "V": 30.8907
  },
  {
    "Line": "L-9",
    "V": 14.5286
  },
  {
    "Line": "L10",
    "V": 15.0715
  },
  {
    "Line": "L11",
    "V": 14.0701
  },
  {
    "Line": "L13",
    "V": 2.9379
  },
  {
    "Line": "L17",
    "V": 31.8231
  },
  {
    "Line": "L18",
    "V": 32.545
  },
  {
    "Line": "L19",
    "V": 14.3549
  },
  {
    "Line": "L20",
    "V": 24.1384
  },
  {
    "Line": "L22",
    "V": 30.5707
  },
  {
    "Line": "L24",
    "V": 25.927
  },
  {
    "Line": "L25",
    "V": 11.8769
  },
  {
    "Line": "L26",
    "V": 25.9142
  },
  {
    "Line": "L27",
    "V": 29.7867
  },
  {
    "Line": "L31",
    "V": 32.8467
  },
  {
    "Line": "L39",
    "V": 24.3456
  },
  {
    "Line": "L40",
    "V": 25.6866
  },
  {
    "Line": "LOVE",
    "V": 3.6432
  },
  {
    "Line": "N01",
    "V": 32.7545
  },
  {
    "Line": "N02",
    "V": 21.4842
  },
  {
    "Line": "N03",
    "V": 3.8011
  },
  {
    "Line": "N11",
    "V": 4.0075
  },
  {
    "Line": "N13",
    "V": 34.6321
  },
  {
    "Line": "N21",
    "V": 25.957
  },
  {
    "Line": "N22",
    "V": 22.9879
  },
  {
    "Line": "N24",
    "V": 12.5309
  },
  {
    "Line": "N25",
    "V": 22.6321
  },
  {
    "Line": "N31",
    "V": 33.067
  },
  {
    "Line": "N32",
    "V": 24.5864
  },
  {
    "Line": "N33",
    "V": 23.8266
  },
  {
    "Line": "N34",
    "V": 31.6054
  },
  {
    "Line": "N35",
    "V": 10.605
  },
  {
    "Line": "N36",
    "V": 18.3355
  },
  {
    "Line": "N37",
    "V": 13.8817
  },
  {
    "Line": "N38",
    "V": 0.2045
  },
  {
    "Line": "N41",
    "V": 33.9076
  },
  {
    "Line": "N43",
    "V": 30.5363
  },
  {
    "Line": "N44",
    "V": 29.2817
  },
  {
    "Line": "N45",
    "V": 15.0502
  },
  {
    "Line": "N46",
    "V": 42.8726
  },
  {
    "Line": "N62",
    "V": 20.1883
  },
  {
    "Line": "N66",
    "V": 1.7519
  },
  {
    "Line": "N72",
    "V": 24.4285
  },
  {
    "Line": "N83",
    "V": 23.8349
  },
  {
    "Line": "N88",
    "V": 11.2948
  },
  {
    "Line": "N91",
    "V": 26.5664
  },
  {
    "Line": "N95",
    "V": 27.5536
  },
  {
    "Line": "Rezerwa R-2",
    "V": 17.5053
  },
  {
    "Line": "Z-1",
    "V": 22.4717
  },
  {
    "Line": "Z-2",
    "V": 16.6707
  },
  {
    "Line": "Z83",
    "V": 22.0005
  }
]
